pipen_deprecated.py
pipen_deprecated-1.0.0.dist-info/METADATA
pipen_deprecated-1.0.0.dist-info/WHEEL
pipen_deprecated-1.0.0.dist-info/entry_points.txt
pipen_deprecated-1.0.0.dist-info/RECORD
